mcp_coroot/__init__.py
mcp_coroot/client.py
mcp_coroot/server.py
mcp_coroot-0.1.1.dist-info/METADATA
mcp_coroot-0.1.1.dist-info/WHEEL
mcp_coroot-0.1.1.dist-info/entry_points.txt
mcp_coroot-0.1.1.dist-info/licenses/LICENSE
mcp_coroot-0.1.1.dist-info/RECORD
