Metadata-Version: 2.4
Name: mcp-coroot
Version: 0.1.1
Summary: MCP server for Coroot observability platform
Project-URL: Homepage, https://github.com/jamesbrink/mcp-coroot
Project-URL: Repository, https://github.com/jamesbrink/mcp-coroot
Project-URL: Issues, https://github.com/jamesbrink/mcp-coroot/issues
Project-URL: Documentation, https://github.com/jamesbrink/mcp-coroot#readme
Author-email: James Brink <james@jamesbrink.net>
Maintainer-email: James Brink <james@jamesbrink.net>
License: MIT
License-File: LICENSE
Keywords: apm,coroot,mcp,metrics,monitoring,observability,tracing
Classifier: Development Status :: 4 - Beta
Classifier: Intended Audience :: Developers
Classifier: License :: OSI Approved :: MIT License
Classifier: Programming Language :: Python :: 3
Classifier: Programming Language :: Python :: 3.11
Classifier: Programming Language :: Python :: 3.12
Classifier: Programming Language :: Python :: 3.13
Classifier: Topic :: Software Development :: Libraries :: Python Modules
Classifier: Topic :: System :: Monitoring
Requires-Python: >=3.11
Requires-Dist: fastmcp>=2.10.6
Requires-Dist: httpx>=0.28.1
Requires-Dist: python-dotenv>=1.1.1
